monaco_racing_report/__init__.py
monaco_racing_report/build_report.py
monaco_racing_report/main.py
monaco_racing_report/print_report.py
monaco_racing_report/report.py
monaco_racing_report-0.1.5.dist-info/LICENSE
monaco_racing_report-0.1.5.dist-info/WHEEL
monaco_racing_report-0.1.5.dist-info/METADATA
monaco_racing_report-0.1.5.dist-info/RECORD
