Metadata-Version: 2.1
Name: monaco-racing-report
Version: 0.1.5
Summary: Report of Monaco 2018 Racing
License: MIT
Author: Skazko Anton
Author-email: sk.anton06@gmail.com
Requires-Python: >=3.8,<4.0
Classifier: License :: OSI Approved :: MIT License
Classifier: Programming Language :: Python :: 3
Classifier: Programming Language :: Python :: 3.10
Classifier: Programming Language :: Python :: 3.8
Classifier: Programming Language :: Python :: 3.9
